[
    {
        "Title Barang": "PANFILA UPRIGHT REF PRFU4150VB",
        "Harga Barang": "Rp 9.877.055",
        "Gambar Barang": "https://loginmegastore.com/uploads/product/0134-0510-0165_thumb.png?w=400&h=400&fit=contain",
        "Page": 1
    },
    {
        "Title Barang": "AQUA 4D REF AQRCTD506RGG(BK)",
        "Harga Barang": "Rp 8.187.005",
        "Gambar Barang": "https://loginmegastore.com/uploads/product/0317-0177-0303_thumb.png?w=400&h=400&fit=contain",
        "Page": 1
    },
    {
        "Title Barang": "AQUA 2D REF AQR415IMBK",
        "Harga Barang": "Rp 5.442.075",
        "Gambar Barang": "https://loginmegastore.com/uploads/product/0317-0175-0279_thumb.jpg?w=400&h=400&fit=contain",
        "Page": 1
    },
    {
        "Title Barang": "SHARP 2D REF SJ236MNHS",
        "Harga Barang": "Rp 2.897.025",
        "Gambar Barang": "https://loginmegastore.com/uploads/product/0153-0175-1121_thumb.jpeg?w=400&h=400&fit=contain",
        "Page": 1
    },
    {
        "Title Barang": "SHARP 1D REF SJN162NHS",
        "Harga Barang": "Rp 1.777.070",
        "Gambar Barang": "https://loginmegastore.com/uploads/product/AA004225_thumb.jpeg?w=400&h=400&fit=contain",
        "Page": 1
    },
    {
        "Title Barang": "SAMSUNG 2D REF RT19M300BGS",
        "Harga Barang": "Rp 3.727.040",
        "Gambar Barang": "https://loginmegastore.com/uploads/product/AA002214_thumb1.jpg?w=400&h=400&fit=contain",
        "Page": 1
    },
    {
        "Title Barang": "SHARP 2D REF SJ316MNHS",
        "Harga Barang": "Rp 3.397.010",
        "Gambar Barang": "https://loginmegastore.com/uploads/product/0153-0175-1122_thumb.png?w=400&h=400&fit=contain",
        "Page": 1
    },
    {
        "Title Barang": "HISENSE 1D REF RR198D4IBN",
        "Harga Barang": "Rp 1.746.005",
        "Gambar Barang": "https://loginmegastore.com/uploads/product/0535-0174-0080_thumb.png?w=400&h=400&fit=contain",
        "Page": 1
    },
    {
        "Title Barang": "TCL 4D REF P500CD",
        "Harga Barang": "Rp 7.647.025",
        "Gambar Barang": "https://loginmegastore.com/uploads/product/0162-0180-0241_thumb.png?w=400&h=400&fit=contain",
        "Page": 1
    },
    {
        "Title Barang": "SAMSUNG 2D REF RT25FARBDSA",
        "Harga Barang": "Rp 5.599.015",
        "Gambar Barang": "https://loginmegastore.com/uploads/product/AA002220_thumb1.jpg?w=400&h=400&fit=contain",
        "Page": 1
    },
    {
        "Title Barang": "SHARP 1D REF SJX197WDW",
        "Harga Barang": "Rp 2.197.065",
        "Gambar Barang": "https://loginmegastore.com/uploads/product/0153-0174-1120_thumb.jpeg?w=400&h=400&fit=contain",
        "Page": 1
    },
    {
        "Title Barang": "AQUA 1D REF AQRD185MDS",
        "Harga Barang": "Rp 1.777.070",
        "Gambar Barang": "https://loginmegastore.com/uploads/product/0317-0174-0253_thumb.png?w=400&h=400&fit=contain",
        "Page": 1
    },
    {
        "Title Barang": "AQUA 1D REF AQRD225MDS",
        "Harga Barang": "Rp 2.037.085",
        "Gambar Barang": "https://loginmegastore.com/uploads/product/0317-0174-0255_thumb.png?w=400&h=400&fit=contain",
        "Page": 1
    },
    {
        "Title Barang": "SHARP 2D REF SJ246XGMR",
        "Harga Barang": "Rp 3.237.030",
        "Gambar Barang": "https://loginmegastore.com/uploads/product/AA002854_thumb1.jpg?w=400&h=400&fit=contain",
        "Page": 1
    },
    {
        "Title Barang": "SAMSUNG 2D REF RT22FARBDSA",
        "Harga Barang": "Rp 4.837.020",
        "Gambar Barang": "https://loginmegastore.com/uploads/product/AA002218_thumb.png?w=400&h=400&fit=contain",
        "Page": 1
    },
    {
        "Title Barang": "TOSHIBA 2D REF GRB25ISP",
        "Harga Barang": "Rp 3.127.020",
        "Gambar Barang": "https://loginmegastore.com/uploads/product/0172-0175-0417_thumb.png?w=400&h=400&fit=contain",
        "Page": 1
    },
    {
        "Title Barang": "SAMSUNG 2D REF RT38CG6420B1SE",
        "Harga Barang": "Rp 7.799.025",
        "Gambar Barang": "https://loginmegastore.com/uploads/product/0144-0175-1981_thumb.png?w=400&h=400&fit=contain",
        "Page": 2
    },
    {
        "Title Barang": "HITACHI 2D REF RWB640PGD1GCK",
        "Harga Barang": "Rp 17.577.090",
        "Gambar Barang": "https://loginmegastore.com/uploads/product/AA004106_thumb.jpg?w=400&h=400&fit=contain",
        "Page": 2
    },
    {
        "Title Barang": "PANFILA 4D REF PRFM5511GB",
        "Harga Barang": "Rp 12.377.075",
        "Gambar Barang": "https://loginmegastore.com/uploads/product/0134-0177-0163_thumb.png?w=400&h=400&fit=contain",
        "Page": 2
    },
    {
        "Title Barang": "MODENA 2D REF RF2650TGDS",
        "Harga Barang": "Rp 4.197.005",
        "Gambar Barang": "https://loginmegastore.com/uploads/product/0121-0175-0489_thumb.png?w=400&h=400&fit=contain",
        "Page": 2
    },
    {
        "Title Barang": "HISENSE 2D REF RT469N4IWPBU",
        "Harga Barang": "Rp 4.977.050",
        "Gambar Barang": "https://loginmegastore.com/uploads/product/0535-0175-0078_thumb.png?w=400&h=400&fit=contain",
        "Page": 2
    },
    {
        "Title Barang": "AQUA 4D REF AQRTTD546RBG(WT)",
        "Harga Barang": "Rp 9.487.080",
        "Gambar Barang": "https://loginmegastore.com/uploads/product/0317-0177-0341_thumb.png?w=400&h=400&fit=contain",
        "Page": 2
    },
    {
        "Title Barang": "SHARP 4D REF SJIF51PGCG",
        "Harga Barang": "Rp 9.699.000",
        "Gambar Barang": "https://loginmegastore.com/uploads/product/AA003913_thumb.png?w=400&h=400&fit=contain",
        "Page": 2
    },
    {
        "Title Barang": "AQUA 4D REF AQRCTD746RAG(BK)U1",
        "Harga Barang": "Rp 16.252.030",
        "Gambar Barang": "https://loginmegastore.com/uploads/product/0317-0177-0300_thumb.png?w=400&h=400&fit=contain",
        "Page": 2
    },
    {
        "Title Barang": "SHARP 1D REF SJX197MGDP",
        "Harga Barang": "Rp 2.137.025",
        "Gambar Barang": "https://loginmegastore.com/uploads/product/AA003801_thumb1.jpg?w=400&h=400&fit=contain",
        "Page": 2
    },
    {
        "Title Barang": "PANFILA 4D REF PRFM4311GB",
        "Harga Barang": "Rp 10.577.015",
        "Gambar Barang": "https://loginmegastore.com/uploads/product/0134-0177-0162_thumb.png?w=400&h=400&fit=contain",
        "Page": 2
    },
    {
        "Title Barang": "SAMSUNG 2D REF RT22FARBDB1/SE",
        "Harga Barang": "Rp 4.937.055",
        "Gambar Barang": "https://loginmegastore.com/uploads/product/AA004108_thumb.png?w=400&h=400&fit=contain",
        "Page": 2
    },
    {
        "Title Barang": "LG 2D REF GNB332PGFB",
        "Harga Barang": "Rp 7.337.040",
        "Gambar Barang": "https://loginmegastore.com/uploads/product/0103-0175-1445_thumb.png?w=400&h=400&fit=contain",
        "Page": 2
    },
    {
        "Title Barang": "SHARP 1D REF SJX197MGDB",
        "Harga Barang": "Rp 2.137.025",
        "Gambar Barang": "https://loginmegastore.com/uploads/product/AA003800_thumb1.jpg?w=400&h=400&fit=contain",
        "Page": 2
    },
    {
        "Title Barang": "HITACHI 4D REF RWB64VGD0XMIR",
        "Harga Barang": "Rp 26.527.040",
        "Gambar Barang": "https://loginmegastore.com/uploads/product/AA003959_thumb.png?w=400&h=400&fit=contain",
        "Page": 2
    },
    {
        "Title Barang": "AQUA 2D REF AQRDTM285RAV(MX)",
        "Harga Barang": "Rp 3.727.040",
        "Gambar Barang": "https://loginmegastore.com/uploads/product/0317-0175-0319_thumb.png?w=400&h=400&fit=contain",
        "Page": 2
    },
    {
        "Title Barang": "LG SIDE BY SIDE 2D GCFB507PQAM",
        "Harga Barang": "Rp 9.622.265",
        "Gambar Barang": "https://loginmegastore.com/uploads/product/AA004294_thumb.jpeg?w=400&h=400&fit=contain",
        "Page": 2
    },
    {
        "Title Barang": "HITACHI 2D REF RB33PGD8BSL",
        "Harga Barang": "Rp 7.427.005",
        "Gambar Barang": "https://loginmegastore.com/uploads/product/AA000769_thumb.jpeg?w=400&h=400&fit=contain",
        "Page": 3
    },
    {
        "Title Barang": "SHARP 2D REF SJ317MGDB",
        "Harga Barang": "Rp 3.497.045",
        "Gambar Barang": "https://loginmegastore.com/uploads/product/AA003795_thumb.jpg?w=400&h=400&fit=contain",
        "Page": 3
    },
    {
        "Title Barang": "SHARP 2D REF SJ237MGDB",
        "Harga Barang": "Rp 3.077.050",
        "Gambar Barang": "https://loginmegastore.com/uploads/product/AA003792_thumb.jpg?w=400&h=400&fit=contain",
        "Page": 3
    },
    {
        "Title Barang": "LG SIDE BY SIDE 2D GCB257SQYL",
        "Harga Barang": "Rp 13.377.045",
        "Gambar Barang": "https://loginmegastore.com/uploads/product/0103-0178-1382_thumb.png?w=400&h=400&fit=contain",
        "Page": 3
    },
    {
        "Title Barang": "SAMSUNG 2D REF RT42CG6420B1SE",
        "Harga Barang": "Rp 8.099.035",
        "Gambar Barang": "https://loginmegastore.com/uploads/product/0144-0175-1978_thumb.png?w=400&h=400&fit=contain",
        "Page": 3
    },
    {
        "Title Barang": "SHARP 2D REF SJ237MGDP",
        "Harga Barang": "Rp 3.077.050",
        "Gambar Barang": "https://loginmegastore.com/uploads/product/AA003793_thumb.jpg?w=400&h=400&fit=contain",
        "Page": 3
    },
    {
        "Title Barang": "SAMSUNG 2D REF RT25FARBDB1/SE",
        "Harga Barang": "Rp 5.777.045",
        "Gambar Barang": "https://loginmegastore.com/uploads/product/AA004109_thumb.png?w=400&h=400&fit=contain",
        "Page": 3
    },
    {
        "Title Barang": "AQUA 2D REF AQRDTM265CBP(ME)",
        "Harga Barang": "Rp 3.027.080",
        "Gambar Barang": "https://loginmegastore.com/uploads/product/0317-0175-0345_thumb.png?w=400&h=400&fit=contain",
        "Page": 3
    },
    {
        "Title Barang": "AQUA 2D REF AQRDTM305RAV(MX)",
        "Harga Barang": "Rp 4.227.025",
        "Gambar Barang": "https://loginmegastore.com/uploads/product/0317-0175-0320_thumb.png?w=400&h=400&fit=contain",
        "Page": 3
    },
    {
        "Title Barang": "SHARP 2D REF SJ326XGCP",
        "Harga Barang": "Rp 4.177.055",
        "Gambar Barang": "https://loginmegastore.com/uploads/product/0153-0175-1155_thumb.jpg?w=400&h=400&fit=contain",
        "Page": 3
    },
    {
        "Title Barang": "HITACHI 2D REF RBG41PGD6XXGR",
        "Harga Barang": "Rp 9.397.020",
        "Gambar Barang": "https://loginmegastore.com/uploads/product/AA000771_thumb.jpeg?w=400&h=400&fit=contain",
        "Page": 3
    },
    {
        "Title Barang": "SHARP 2D REF SJ317MGDP",
        "Harga Barang": "Rp 3.497.045",
        "Gambar Barang": "https://loginmegastore.com/uploads/product/AA003794_thumb.jpg?w=400&h=400&fit=contain",
        "Page": 3
    },
    {
        "Title Barang": "HITACHI 2D REF HRTN5230MXID",
        "Harga Barang": "Rp 5.127.055",
        "Gambar Barang": "https://loginmegastore.com/uploads/product/0081-0175-0395_thumb.png?w=400&h=400&fit=contain",
        "Page": 3
    },
    {
        "Title Barang": "SHARP 2D REF SJ326SIGK",
        "Harga Barang": "Rp 3.937.085",
        "Gambar Barang": "https://loginmegastore.com/uploads/product/0153-0175-1172_thumb.png?w=400&h=400&fit=contain",
        "Page": 3
    },
    {
        "Title Barang": "HISENSE 2D REF RT469N4IWU",
        "Harga Barang": "Rp 4.827.045",
        "Gambar Barang": "https://loginmegastore.com/uploads/product/0535-0175-0095_thumb.png?w=400&h=400&fit=contain",
        "Page": 3
    },
    {
        "Title Barang": "MODENA 4D REF RF4310MABK",
        "Harga Barang": "Rp 9.177.000",
        "Gambar Barang": "https://loginmegastore.com/uploads/product/0121-0180-0485_thumb.png?w=400&h=400&fit=contain",
        "Page": 3
    },
    {
        "Title Barang": "BORISH BEINZ EGG BOX ACC BBKW LT01 WH",
        "Harga Barang": "Rp 93.575",
        "Gambar Barang": "https://loginmegastore.com/uploads/product/0033-0751-0399_thumb.jpg?w=400&h=400&fit=contain",
        "Page": 4
    },
    {
        "Title Barang": "BERVIN MULTIFUNCTION STAND BOS 100 GREY",
        "Harga Barang": "Rp 437.000",
        "Gambar Barang": "https://loginmegastore.com/uploads/product/0030-0029-0108_thumb.png?w=400&h=400&fit=contain",
        "Page": 4
    },
    {
        "Title Barang": "BERVIN MSTNACCREF BOS 200 DARKGREY",
        "Harga Barang": "Rp 577.030",
        "Gambar Barang": "https://loginmegastore.com/uploads/product/0030-0029-0121_thumb.png?w=400&h=400&fit=contain",
        "Page": 4
    },
    {
        "Title Barang": "BERVIN MULTIFUNCTION STAND BOS 50 GREY",
        "Harga Barang": "Rp 347.035",
        "Gambar Barang": "https://loginmegastore.com/uploads/product/0030-0029-0124_thumb.png?w=400&h=400&fit=contain",
        "Page": 4
    },
    {
        "Title Barang": "BERVIN MULTIFUNCTION STAND WM BFSA151MS",
        "Harga Barang": "Rp 607.050",
        "Gambar Barang": "https://loginmegastore.com/uploads/product/0030-0752-0295_thumb.png?w=400&h=400&fit=contain",
        "Page": 4
    },
    {
        "Title Barang": "BERVIN MULTIFUNCTION STAND WM BWSA121MG",
        "Harga Barang": "Rp 477.090",
        "Gambar Barang": "https://loginmegastore.com/uploads/product/0030-0752-0293_thumb.png?w=400&h=400&fit=contain",
        "Page": 4
    },
    {
        "Title Barang": "BERVIN MULTIFUNCTION STAND WM BFSA151MG",
        "Harga Barang": "Rp 607.050",
        "Gambar Barang": "https://loginmegastore.com/uploads/product/0030-0752-0296_thumb.png?w=400&h=400&fit=contain",
        "Page": 4
    },
    {
        "Title Barang": "LUNA MULTIFUNCTION STAND WM LWSA120 GREY",
        "Harga Barang": "Rp 427.025",
        "Gambar Barang": "https://loginmegastore.com/uploads/product/BC000155_thumb.jpg?w=400&h=400&fit=contain",
        "Page": 4
    },
    {
        "Title Barang": "LUNA MULTIFUNCTION STAND LRSA70 GREY",
        "Harga Barang": "Rp 347.035",
        "Gambar Barang": "https://loginmegastore.com/uploads/product/BC000171_thumb.jpg?w=400&h=400&fit=contain",
        "Page": 4
    },
    {
        "Title Barang": "BERVIN MULTIFUNCTION STAND WM BFSA151DB",
        "Harga Barang": "Rp 607.050",
        "Gambar Barang": "https://loginmegastore.com/uploads/product/0030-0752-0294_thumb.png?w=400&h=400&fit=contain",
        "Page": 4
    },
    {
        "Title Barang": "LUNA MULTIFUNCTION STAND LRSF10 GREY",
        "Harga Barang": "Rp 237.025",
        "Gambar Barang": "https://loginmegastore.com/uploads/product/BC001369_thumb.jpg?w=400&h=400&fit=contain",
        "Page": 4
    },
    {
        "Title Barang": "PANFILA SIDE BY SIDE 2D PRFB5611GB",
        "Harga Barang": "Rp 9.877.055",
        "Gambar Barang": "https://loginmegastore.com/uploads/product/0134-0178-0160_thumb.png?w=400&h=400&fit=contain",
        "Page": 4
    },
    {
        "Title Barang": "PANFILA SIDE BY SIDE 2D PRFB6411GB",
        "Harga Barang": "Rp 11.677.020",
        "Gambar Barang": "https://loginmegastore.com/uploads/product/0134-0178-0161_thumb.png?w=400&h=400&fit=contain",
        "Page": 4
    },
    {
        "Title Barang": "PANFILA 4D REF PRFM4310",
        "Harga Barang": "Rp 9.977.090",
        "Gambar Barang": "https://loginmegastore.com/uploads/product/0134-0180-0141_thumb.jpeg?w=400&h=400&fit=contain",
        "Page": 4
    },
    {
        "Title Barang": "SHARP 4D REF SJIF51PGBK",
        "Harga Barang": "Rp 9.877.055",
        "Gambar Barang": "https://loginmegastore.com/uploads/product/AA003914_thumb.jpg?w=400&h=400&fit=contain",
        "Page": 4
    },
    {
        "Title Barang": "BEKO SIDE BY SIDE 3D GNO610E00GUID",
        "Harga Barang": "Rp 11.177.035",
        "Gambar Barang": "https://loginmegastore.com/uploads/product/0477-0179-0038_thumb.png?w=400&h=400&fit=contain",
        "Page": 4
    },
    {
        "Title Barang": "LG SIDE BY SIDE 4D GCV22FFQMB",
        "Harga Barang": "Rp 22.427.030",
        "Gambar Barang": "https://loginmegastore.com/uploads/product/0103-0180-1454_thumb.png?w=400&h=400&fit=contain",
        "Page": 5
    },
    {
        "Title Barang": "PANFILA SIDE BY SIDE 2D PRFB5610",
        "Harga Barang": "Rp 8.977.025",
        "Gambar Barang": "https://loginmegastore.com/uploads/product/0134-0178-0140_thumb.jpeg?w=400&h=400&fit=contain",
        "Page": 5
    },
    {
        "Title Barang": "HITACHI SIDE BY SIDE 2D HRSN9552DDXID",
        "Harga Barang": "Rp 10.777.085",
        "Gambar Barang": "https://loginmegastore.com/uploads/product/0081-0178-0375_thumb.png?w=400&h=400&fit=contain",
        "Page": 5
    },
    {
        "Title Barang": "SAMSUNG SIDE BY SIDE 2D RS70F65QNTSE",
        "Harga Barang": "Rp 14.399.055",
        "Gambar Barang": "https://loginmegastore.com/uploads/product/0144-0178-2088_thumb.png?w=400&h=400&fit=contain",
        "Page": 5
    },
    {
        "Title Barang": "SAMSUNG SIDE BY SIDE 2D RS57DG4000M9",
        "Harga Barang": "Rp 9.499.050",
        "Gambar Barang": "https://loginmegastore.com/uploads/product/0144-0178-2087_thumb.png?w=400&h=400&fit=contain",
        "Page": 5
    },
    {
        "Title Barang": "SAMSUNG SIDE BY SIDE 2D RS70F65QNFSE",
        "Harga Barang": "Rp 14.999.075",
        "Gambar Barang": "https://loginmegastore.com/uploads/product/0144-0178-2089_thumb.png?w=400&h=400&fit=contain",
        "Page": 5
    },
    {
        "Title Barang": "HISENSE SIDE BY SIDE 2D RS808N4IBU",
        "Harga Barang": "Rp 10.177.065",
        "Gambar Barang": "https://loginmegastore.com/uploads/product/0535-0178-0077_thumb.png?w=400&h=400&fit=contain",
        "Page": 5
    },
    {
        "Title Barang": "MODENA SIDE BY SIDE 2D RF4670SABK",
        "Harga Barang": "Rp 7.737.085",
        "Gambar Barang": "https://loginmegastore.com/uploads/product/0121-0178-0487_thumb.png?w=400&h=400&fit=contain",
        "Page": 5
    },
    {
        "Title Barang": "PANASONIC SIDE BY SIDE 2D NRSC631BGHD",
        "Harga Barang": "Rp 12.627.020",
        "Gambar Barang": "https://loginmegastore.com/uploads/product/0133-0178-0785_thumb.png?w=400&h=400&fit=contain",
        "Page": 5
    },
    {
        "Title Barang": "SHARP 2D REF SJ426GIGW",
        "Harga Barang": "Rp 4.920.000",
        "Gambar Barang": "https://loginmegastore.com/uploads/product/202603/product-v3suzpx85ngjaej2qhav1v5i.png?w=400&h=400&fit=contain",
        "Page": 5
    },
    {
        "Title Barang": "PB CONTAINER BOX JP004 KOTAK CONTAINER MAKANAN KULKAS LARGE",
        "Harga Barang": "Rp 96.425",
        "Gambar Barang": "https://loginmegastore.com/uploads/product/0707-0412-0043_thumb.png?w=400&h=400&fit=contain",
        "Page": 5
    },
    {
        "Title Barang": "PB CONTAINER BOX JP001 KOTAK CONTAINER MAKANAN KULKAS SMALL",
        "Harga Barang": "Rp 95.000",
        "Gambar Barang": "https://loginmegastore.com/uploads/product/0707-0412-0041_thumb.png?w=400&h=400&fit=contain",
        "Page": 5
    },
    {
        "Title Barang": "PB CONTAINER BOX JP002 KOTAK CONTAINER MAKANAN KULKAS MEDIUM",
        "Harga Barang": "Rp 84.550",
        "Gambar Barang": "https://loginmegastore.com/uploads/product/0707-0412-0042_thumb.png?w=400&h=400&fit=contain",
        "Page": 5
    },
    {
        "Title Barang": "PB CONTAINER BOX JP101 KOTAK CONTAINER MAKANAN KULKAS KALENG",
        "Harga Barang": "Rp 31.825",
        "Gambar Barang": "https://loginmegastore.com/uploads/product/0707-0412-0044_thumb.png?w=400&h=400&fit=contain",
        "Page": 5
    },
    {
        "Title Barang": "PB FOOD CONTAINER HMC118SB KOTAK PENYIMPANAN MAKANAN KULKAS SMALL BIRU",
        "Harga Barang": "Rp 30.400",
        "Gambar Barang": "https://loginmegastore.com/uploads/product/0707-0357-0023_thumb.png?w=400&h=400&fit=contain",
        "Page": 5
    },
    {
        "Title Barang": "PB FOOD CONTAINER HMC118LW KOTAK PENYIMPANAN MAKANAN KULKAS LARGE PUTIH",
        "Harga Barang": "Rp 47.025",
        "Gambar Barang": "https://loginmegastore.com/uploads/product/0707-0357-0022_thumb.png?w=400&h=400&fit=contain",
        "Page": 5
    }
]